easyprocess/__init__.py
easyprocess/about.py
easyprocess/unicodeutil.py
easyprocess/examples/__init__.py
easyprocess/examples/cmd.py
easyprocess/examples/hello.py
easyprocess/examples/log.py
easyprocess/examples/timeout.py
easyprocess/examples/ver.py
easyprocess/examples/with.py
EasyProcess-1.0.dist-info/LICENSE.txt
EasyProcess-1.0.dist-info/METADATA
EasyProcess-1.0.dist-info/WHEEL
EasyProcess-1.0.dist-info/top_level.txt
EasyProcess-1.0.dist-info/RECORD
