Metadata-Version: 2.1
Name: EasyProcess
Version: 1.0
Summary: Easy to use Python subprocess interface.
Home-page: https://github.com/ponty/easyprocess
Author: ponty
License: BSD
Keywords: subprocess interface
Platform: UNKNOWN
Classifier: License :: OSI Approved :: BSD License
Classifier: Natural Language :: English
Classifier: Operating System :: OS Independent
Classifier: Programming Language :: Python
Classifier: Programming Language :: Python :: 3
Classifier: Programming Language :: Python :: 3 :: Only
Classifier: Programming Language :: Python :: 3.7
Classifier: Programming Language :: Python :: 3.8
Classifier: Programming Language :: Python :: 3.9
Classifier: Programming Language :: Python :: 3.10
